crypt/__init__.py
standard_crypt-3.13.0.dist-info/LICENSE
standard_crypt-3.13.0.dist-info/METADATA
standard_crypt-3.13.0.dist-info/WHEEL
standard_crypt-3.13.0.dist-info/top_level.txt
standard_crypt-3.13.0.dist-info/RECORD
